LICENSE
get_repo/__init__.py
get_repo/cli.py
get_repo/parser.py
get_repo-0.1.3.dist-info/entry_points.txt
get_repo-0.1.3.dist-info/LICENSE
get_repo-0.1.3.dist-info/WHEEL
get_repo-0.1.3.dist-info/METADATA
get_repo-0.1.3.dist-info/RECORD
