Metadata-Version: 2.1
Name: get-repo
Version: 0.1.3
Summary: Small cli utility for cloning git repos in an orderly manner
Home-page: https://github.com/florian42/get-repo
License: MIT
Author: Florian
Author-email: hey@flo.fish
Requires-Python: >=3.10,<4.0
Classifier: License :: OSI Approved :: MIT License
Classifier: Programming Language :: Python :: 3
Classifier: Programming Language :: Python :: 3.10
Requires-Dist: GitPython (>=3.1.27,<4.0.0)
Requires-Dist: git-url-parse (>=1.2.2,<2.0.0)
Requires-Dist: typer (>=0.4.0,<0.5.0)
Project-URL: Repository, https://github.com/florian42/get-repo
